{
  "_comment": "Nominatim query overrides for regions where name+country isn't sufficient. Key is region slug.",
  "overrides": {
    "south-eastern-australia": { "query": "South Eastern Australia", "type": "super-zone", "skip": true, "reason": "Cross-state super-zone, no single admin boundary" },
    "aconcagua-region": { "query": "Aconcagua Valley, Valparaíso Region, Chile" },
    "central-valley-chile": { "query": "Valle Central, Chile", "fallback": "O'Higgins Region, Chile" },
    "coquimbo-region": { "query": "Coquimbo Region, Chile" },
    "southern-region-chile": { "query": "Biobío Region, Chile", "fallback": "Malleco Province, Chile" },
    "atacama": { "query": "Atacama Region, Chile" },
    "serra-gaucha": { "query": "Serra Gaúcha, Rio Grande do Sul, Brazil" },
    "campanha": { "query": "Campanha, Rio Grande do Sul, Brazil" },
    "vale-do-sao-francisco": { "query": "Vale do São Francisco, Brazil", "fallback": "Petrolina, Pernambuco, Brazil" },
    "santa-catarina": { "query": "Santa Catarina, Brazil" },
    "british-columbia": { "query": "British Columbia, Canada" },
    "nova-scotia": { "query": "Nova Scotia, Canada" },
    "ontario": { "query": "Ontario, Canada" },
    "kakheti": { "query": "Kakheti, Georgia" },
    "imereti": { "query": "Imereti, Georgia" },
    "kartli": { "query": "Kartli, Georgia", "fallback": "Shida Kartli, Georgia" },
    "racha-lechkhumi": { "query": "Racha-Lechkhumi and Kvemo Svaneti, Georgia" },
    "samegrelo": { "query": "Samegrelo-Zemo Svaneti, Georgia" },
    "hokkaido": { "query": "Hokkaido, Japan" },
    "nagano": { "query": "Nagano Prefecture, Japan" },
    "osaka": { "query": "Osaka Prefecture, Japan" },
    "yamagata": { "query": "Yamagata Prefecture, Japan" },
    "yamanashi": { "query": "Yamanashi Prefecture, Japan" },
    "codru": { "query": "Codru, Moldova" },
    "stefan-voda": { "query": "Ștefan Vodă District, Moldova" },
    "valul-lui-traian": { "query": "Valul lui Traian, Moldova" },
    "buenos-aires": { "query": "Buenos Aires Province, Argentina" },
    "cordoba": { "query": "Córdoba Province, Argentina" },
    "entre-rios": { "query": "Entre Ríos Province, Argentina" },
    "jujuy": { "query": "Jujuy Province, Argentina" },
    "la-rioja": { "query": "La Rioja Province, Argentina" },
    "mendoza": { "query": "Mendoza Province, Argentina" },
    "patagonia": { "query": "Río Negro Province, Argentina", "note": "Patagonia wine region centered on Río Negro" },
    "salta": { "query": "Salta Province, Argentina" },
    "san-juan": { "query": "San Juan Province, Argentina" },
    "san-luis": { "query": "San Luis Province, Argentina" },
    "cafayate": { "query": "Cafayate, Salta, Argentina" },
    "lujan-de-cuyo": { "query": "Luján de Cuyo, Mendoza, Argentina" },
    "maipu": { "query": "Maipú, Mendoza, Argentina" },
    "uco-valley": { "query": "Valle de Uco, Mendoza, Argentina" },
    "breede-river-valley": { "query": "Breede River Valley, Western Cape, South Africa" },
    "cape-south-coast": { "query": "Cape South Coast, South Africa", "fallback": "Overberg, Western Cape, South Africa" },
    "coastal-region": { "query": "Cape Winelands, Western Cape, South Africa" },
    "western-cape": { "query": "Western Cape, South Africa" },
    "constantia": { "query": "Constantia, Cape Town, South Africa" },
    "durbanville": { "query": "Durbanville, Cape Town, South Africa" },
    "elgin": { "query": "Elgin, Western Cape, South Africa" },
    "elim": { "query": "Elim, Western Cape, South Africa" },
    "paarl": { "query": "Paarl, Western Cape, South Africa" },
    "robertson": { "query": "Robertson, Western Cape, South Africa" },
    "stellenbosch": { "query": "Stellenbosch, Western Cape, South Africa" },
    "swartland": { "query": "Swartland, Western Cape, South Africa" },
    "walker-bay": { "query": "Walker Bay, Western Cape, South Africa", "fallback": "Hermanus, Western Cape, South Africa" },
    "worcester": { "query": "Worcester, Western Cape, South Africa" },
    "aargau": { "query": "Canton of Aargau, Switzerland" },
    "bern": { "query": "Canton of Bern, Switzerland" },
    "fribourg": { "query": "Canton of Fribourg, Switzerland" },
    "geneva": { "query": "Canton of Geneva, Switzerland" },
    "graubunden": { "query": "Canton of Graubünden, Switzerland" },
    "luzern": { "query": "Canton of Lucerne, Switzerland" },
    "neuchatel": { "query": "Canton of Neuchâtel, Switzerland" },
    "schaffhausen": { "query": "Canton of Schaffhausen, Switzerland" },
    "st-gallen": { "query": "Canton of St. Gallen, Switzerland" },
    "thurgau": { "query": "Canton of Thurgau, Switzerland" },
    "ticino": { "query": "Canton of Ticino, Switzerland" },
    "valais": { "query": "Canton of Valais, Switzerland" },
    "vaud": { "query": "Canton of Vaud, Switzerland" },
    "zurich": { "query": "Canton of Zürich, Switzerland" }
  }
}
